
# 为啥需要 type system?

## `type` 就是契约
- At the hardware level, the machine does not know types in the way humans or high-level programming languages do. 硬件级别就是电信号了。`type` 这种概念不存在。
- Bits are just bits (0s and 1s), and the CPU/memory has no intrinsic understanding of "integers," "strings," or "objects." 
- But types exist in programming languages to `impose structure on those raw bits`, guiding both the `programmer` and the `compiler/interpreter` on how to `interpret and manipulate` data safely and meaningfully. 

## Bridging Human Intent <-> Machine Execution
Types act as a `contract`
- For `humans`: They make code `readable` and `intentional` (e.g., int age vs. string name).  
- For `compilers`: They generate `correct`, `optimized` machine code (e.g., using ADD vs. FADD for integers vs. floats). 编译器根据数据类型使用相应的指令 
- For `safety`: They prevent `invalid` operations (e.g., multiplying a string by a file handle).

# 硬件视角下的数据

## Bits Are Just Bits

> 按照硬件电路的设计，就是一系列电信号而已。

### No inherent types

> 没有所谓的类型。

To the CPU, memory is a giant array of bytes. When you write 42 (integer) or "hello" (string), the machine sees only binary patterns like 00101010 or 01101000 01100101 01101100 01101100 01101111.  

### Operations are "type-agnostic"
> 给定一个指令，指令就会按照设计好的功能来使用 bits, 不管这个 bits 到底是啥。


The CPU executes instructions (e.g., ADD, MOV) based on the binary values in registers, not their "meaning." For example:  
- ADD treats bits as integers (using `arithmetic circuits`).
- MOV copies bits `blindly` from one location to another.  
- The `same bits` could represent an integer, a float, or part of a string, depending on context.


# How Types Work "Under the Hood"？

**`Types are a human/compiler abstraction layered on top of raw bits`**

Here’s how they translate to the machine:
1.  Compiler/Interpreter Assigns Meaning
- A high-level language (e.g., C, Python) assigns semantic meaning to bits using types. For example:  
- int x = 42: The compiler allocates 4 bytes (32 bits) and encodes 42 as 00101010..., then enforces that x can only be used in integer operations (e.g., x + 5).  
- float y = 3.14: The same 4 bytes are interpreted as an IEEE 754 floating-point number.  
- char* s = "hello": The compiler stores the ASCII codes for each character in memory and treats the variable as a pointer to the first byte.  

Without types, the compiler wouldn’t know `how to generate correct machine code` (e.g., integer vs. floating-point arithmetic instructions).

2. Runtime Type Tracking (Dynamically Typed Languages)
In languages like Python or JavaScript, types are `checked at runtime`. For example:

```python
x = 42          # Interpreter tags `x` as an integer internally.
x = "hello"     # Later, the tag changes to "string."
```
The interpreter keeps metadata (e.g., type tags) to track what the bits represent. This adds overhead but allows flexibility.

# What Happens Without High-Level Type Abstractions?

If you remove types from the equation (e.g., programming in raw assembly or using memory pointers without safeguards):
##  Ambiguous Interpretation
The same bits can be misused as different types, leading to chaos:  

// C code (no runtime type checking)
```c
int x = 42;
float* y = (float*)&x; // Reinterpret the bits of `x` as a float.
printf("%f", *y);      // Prints nonsense: 42 as a float ≈ 5.9e-44.
```
## Undefined Behavior
• Memory corruption: Writing a string into memory allocated for an integer:

```c
int* arr = malloc(sizeof(int) * 5);
arr[5] = 100; // Buffer overflow (undefined behavior).
```
• Security vulnerabilities: Treating data as executable code (e.g., injection attacks).
##  No Guardrails
• You could "add" a string to a file handle, and the CPU would try to execute it, resulting in crashes or garbage output.

# java 代码理解

## Square.java

```java
class Square {
    static int square(int num) {
        return num * num;
    }

   static float square(float num){
        return num * num;
   }

    static long square(long num){
        return num * num;
   }
   
}
```

## Square 字节码查看

javap -c Square 
```java
class Square {
  Square();
    Code:
       0: aload_0
       1: invokespecial #1                  // Method java/lang/Object."<init>":()V
       4: return

  static int square(int);
    Code:
       0: iload_0
       1: iload_0
       2: imul
       3: ireturn

  static float square(float);
    Code:
       0: fload_0
       1: fload_0
       2: fmul
       3: freturn

  static long square(long);
    Code:
       0: lload_0
       1: lload_0
       2: lmul
       3: lreturn
}
```
可以看到编译器根据 type 使用了对应的 mul 指令
1. 可以看到 int 类型对应的指令有 imul
2. 可以看到 float 类型对应的指令有 fmul
3. 可以看到 long 类型对应的指令有 lmul


# 总结

Types are a tool `for humans`, `not the machine`. Without them, programming would require `manually managing every bit and operation`, akin to writing assembly code for every program—a recipe for bugs and inefficiency



